{
  "kpn_id": 7331426,
  "candidate_name": "TÁLLAI ANDRÁS",
  "source": "https://hvg.hu",
  "scraped_at": "2026-03-22T19:56:23.397087+00:00",
  "item_count": 6,
  "items": [
    {
      "title": "Mi vár Iránra: káosz, véres forradalom vagy amerikai bevonulás? – Fülke Keresztes Imrével, Nagy Gáborral és Földes Andrással",
      "url": "https://hvg.hu/vilag/20260302_iran-kaosz-veres-forradalom-amerikai-bevonulas-trump-khamenei-fulke-podcast",
      "date": null,
      "excerpt": null,
      "source": "hvg.hu",
      "weight": "medium",
      "confidence": "medium",
      "tags": []
    },
    {
      "title": "Mi vár Iránra: káosz, véres forradalom vagy amerikai bevonulás? – Fülke Keresztes Imrével, Nagy Gáborral és Földes Andrással",
      "url": "https://hvg.hu/vilag/20260302_iran-kaosz-veres-forradalom-amerikai-bevonulas-trump-khamenei-fulke-podcast",
      "date": null,
      "excerpt": null,
      "source": "hvg.hu",
      "weight": "medium",
      "confidence": "medium",
      "tags": []
    },
    {
      "title": "Mi vár Iránra: káosz, véres forradalom vagy amerikai bevonulás? – Fülke Keresztes Imrével, Nagy Gáborral és Földes Andrással",
      "url": "https://hvg.hu/vilag/20260302_iran-kaosz-veres-forradalom-amerikai-bevonulas-trump-khamenei-fulke-podcast",
      "date": null,
      "excerpt": null,
      "source": "hvg.hu",
      "weight": "medium",
      "confidence": "medium",
      "tags": []
    },
    {
      "title": "Nagyon vezet a Tisza, Orbán riadót fúj – Fülke élőben Hann Endrével és Németh Andrással",
      "url": "https://hvg.hu/itthon/20260225_20-szazalek-veri-a-tisza-a-fidesz-hann-endre-eloben-fulke",
      "date": null,
      "excerpt": null,
      "source": "hvg.hu",
      "weight": "medium",
      "confidence": "medium",
      "tags": []
    },
    {
      "title": "Nagyon vezet a Tisza, Orbán riadót fúj – Fülke élőben Hann Endrével és Németh Andrással",
      "url": "https://hvg.hu/itthon/20260225_20-szazalek-veri-a-tisza-a-fidesz-hann-endre-eloben-fulke",
      "date": null,
      "excerpt": null,
      "source": "hvg.hu",
      "weight": "medium",
      "confidence": "medium",
      "tags": []
    },
    {
      "title": "Nagyon vezet a Tisza, Orbán riadót fúj – Fülke élőben Hann Endrével és Németh Andrással",
      "url": "https://hvg.hu/itthon/20260225_20-szazalek-veri-a-tisza-a-fidesz-hann-endre-eloben-fulke",
      "date": null,
      "excerpt": null,
      "source": "hvg.hu",
      "weight": "medium",
      "confidence": "medium",
      "tags": []
    }
  ],
  "party": "FIDESZ-KDNP",
  "constituency": "Borsod-Abaúj-Zemplén county, 07. no. constituency",
  "search_name_used": "Tállai András"
}