{
  "kpn_id": 7449210,
  "candidate_name": "DÖME ZSUZSANNA",
  "source": "https://atlatszo.hu",
  "scraped_at": "2026-03-21T20:59:42.004234+00:00",
  "item_count": 3,
  "items": [
    {
      "title": "Nehéz lesz ez így – a Fővárosi Közgyűlés alakuló ülésének tanulságai",
      "url": "https://atlatszo.hu/adat/2024/10/09/nehez-lesz-ez-igy-a-fovarosi-kozgyules-alakulo-ulesenek-tanulsagai/",
      "date": "perc",
      "excerpt": "Egyik pártnak sincsen meg az abszolút többsége, több napirendi pontban sem sikerült megállapodásra jutni.",
      "source": "atlatszo.hu",
      "weight": "high",
      "confidence": "low",
      "tags": [],
      "note": "name match not confirmed — proximity result"
    },
    {
      "title": "Beindult a mémgyár: letarolta az internetet az erdő nélküli lombkoronasétány",
      "url": "https://atlatszo.hu/kozpenz/2023/04/06/beindult-a-memgyar-letarolta-az-internetet-az-erdo-nelkuli-lombkoronasetany/",
      "date": "perc",
      "excerpt": "A legötletesebb képek és videók egy helyen az erdő nélkül épült nyírmártonfalvai lombkoronasétányról.",
      "source": "atlatszo.hu",
      "weight": "high",
      "confidence": "low",
      "tags": [],
      "note": "name match not confirmed — proximity result"
    },
    {
      "title": "Fradi-szív és Yozsefváros – kiélezett ellenzéki küzdelem a fővárosi 6-os körzetben",
      "url": "https://atlatszo.hu/adat/2021/09/16/fradi-sziv-es-yozsefvaros-kielezett-ellenzeki-kuzdelem-a-fovarosi-6-os-korzeteben/",
      "date": "perc",
      "excerpt": "Néhai kocsisor és Fazekas gimnázium, Müpa és Fradi-pálya, gengszterrap és Duna-part, Páva utcai zsinagóga és Teleki tér. Két ezerarcú kerületből...",
      "source": "atlatszo.hu",
      "weight": "high",
      "confidence": "low",
      "tags": [],
      "note": "name match not confirmed — proximity result"
    }
  ],
  "party": "MKKP",
  "constituency": "Borsod-Abaúj-Zemplén county, 03. no. constituency",
  "search_name_used": "Döme Zsuzsanna"
}